<?xml version="1.0" encoding="UTF-8"?>

<xwikidoc>
  <web>GitHubStats</web>
  <name>ListCommitters</name>
  <language/>
  <defaultLanguage/>
  <translation>0</translation>
  <parent>GitHubStats.WebHome</parent>
  <creator>xwiki:XWiki.Admin</creator>
  <author>xwiki:XWiki.Admin</author>
  <customClass/>
  <contentAuthor>xwiki:XWiki.Admin</contentAuthor>
  <creationDate>1342613690000</creationDate>
  <date>1342613720000</date>
  <contentUpdateDate>1342613720000</contentUpdateDate>
  <version>1.1</version>
  <title>All Committers</title>
  <template/>
  <defaultTemplate/>
  <validationScript/>
  <comment/>
  <minorEdit>false</minorEdit>
  <syntaxId>xwiki/2.1</syntaxId>
  <hidden>true</hidden>
  <content>{{groovy}}
def committerDocs = services.query.xwql("from doc.object(GitHubStats.CommitterClass) as committer").execute()
if (committerDocs.size() &gt; 0) {
  println "|=Avatar|=Id|=Repositories|=Aliases"
  committerDocs.each() { docName -&gt;
    def committerDoc = xwiki.getDocument(docName)
    def committerObject = committerDoc.getObject("GitHubStats.CommitterClass")
    def avatar = committerObject.getProperty("avatar").value
    def id = committerObject.getProperty("id").value
    def repositories = committerObject.getProperty("repositories").value
    def aliases = committerObject.getProperty("aliases").value
    println "|[[image:${avatar}]]|[[${id}&gt;&gt;${docName}]]|${repositories.join(', ')}|${aliases.join(', ')}"
  }
}
{{/groovy}}</content>
</xwikidoc>
